veda_lib/BalanceData.py
veda_lib/DimensionReducer.py
veda_lib/FeatureSelector.py
veda_lib/OutlierHandler.py
veda_lib/Preprocessor.py
veda_lib/Veda.py
veda_lib/__init__.py
veda_lib-0.0.7.dist-info/licenses/LICENSE
veda_lib-0.0.7.dist-info/METADATA
veda_lib-0.0.7.dist-info/WHEEL
veda_lib-0.0.7.dist-info/top_level.txt
veda_lib-0.0.7.dist-info/RECORD
